fidor/__init__.py
fidor/main.py
fidor.py-1.0.dist-info/METADATA
fidor.py-1.0.dist-info/WHEEL
fidor.py-1.0.dist-info/top_level.txt
fidor.py-1.0.dist-info/RECORD
