Metadata-Version: 2.1
Name: fidor.py
Version: 1.0
Summary: A generator for random words, sentences and paragraphs.
Home-page: https://github.com/lareithen/fidor
Author: larei
Author-email: larei@nomail.com
